http_dbus_gateway/__init__.py
http_dbus_gateway/static/css/index.css
http_dbus_gateway/static/html/index.html
http_dbus_gateway/static/js/app.js
http_dbus_gateway-0.0.1.dist-info/WHEEL
http_dbus_gateway-0.0.1.dist-info/METADATA
http_dbus_gateway-0.0.1.dist-info/RECORD
